{
  "id": "default",
  "name": "My Sheet",
  "nodes": [
    {
      "children": [
        {
          "children": [
            {
              "children": [],
              "id": "01548911-98ff-409f-98e9-9ba0656d5b2f",
              "settings": {
                "alt": "",
                "gap": 0,
                "height": 50,
                "objectFit": "cover",
                "padding": 0,
                "squared": true,
                "src": "",
                "width": 32
              },
              "type": "image"
            },
            {
              "children": [
                {
                  "children": [
                    {
                      "children": [],
                      "id": "808f18ef-9d87-4147-880f-a3965eeb5349",
                      "settings": {
                        "gap": 0,
                        "label": "Name",
                        "padding": 0,
                        "placeholder": "",
                        "width": 0
                      },
                      "type": "text-input"
                    },
                    {
                      "children": [],
                      "id": "4377add4-4562-4037-8b4f-42be5cfb82de",
                      "settings": {
                        "allowNegative": false,
                        "gap": 0,
                        "hasMax": true,
                        "label": "Level",
                        "max": 20,
                        "padding": 0
                      },
                      "type": "counter"
                    }
                  ],
                  "id": "fe8ddbd0-2c00-47d4-97b6-d416ae5fc90a",
                  "settings": {
                    "direction": "horizontal",
                    "gap": 8,
                    "padding": 0,
                    "title": "Container",
                    "width": 0
                  },
                  "type": "container"
                },
                {
                  "children": [
                    {
                      "children": [],
                      "id": "8a1f1344-f3c9-4ef6-9b76-6f0a0f9065e5",
                      "settings": {
                        "gap": 0,
                        "label": "Specie",
                        "padding": 0,
                        "width": 0
                      },
                      "type": "specie"
                    },
                    {
                      "children": [],
                      "id": "503935c6-f13e-406a-851d-c452284f0512",
                      "settings": {
                        "gap": 0,
                        "label": "Origin",
                        "padding": 0,
                        "placeholder": ""
                      },
                      "type": "text-input"
                    }
                  ],
                  "id": "619b245c-5f40-4a5b-80e2-a413bf66612b",
                  "settings": {
                    "direction": "horizontal",
                    "gap": 8,
                    "padding": 0,
                    "title": "Container",
                    "width": 0
                  },
                  "type": "container"
                },
                {
                  "children": [],
                  "id": "ad46c30b-0450-4938-be6a-29885dbd4fd2",
                  "settings": {
                    "allowMulticlass": true,
                    "gap": 0,
                    "label": "Class",
                    "padding": 0
                  },
                  "type": "class-selector"
                }
              ],
              "id": "9bebf3e8-25b8-4be5-a5d9-78a235c80ec3",
              "settings": {
                "gap": 4,
                "padding": 8,
                "title": "Character Settings"
              },
              "type": "section"
            }
          ],
          "id": "81ed88ca-f894-496b-817d-5847eba00540",
          "settings": {
            "direction": "horizontal",
            "gap": 10,
            "padding": 0,
            "title": "Character settings",
            "width": 0
          },
          "type": "container"
        },
        {
          "children": [
            {
              "children": [],
              "id": "c83a973d-d448-4ab1-bd59-c7eebdfc30d8",
              "settings": {
                "columns": 6,
                "gap": 10,
                "padding": 0,
                "statKeys": [],
                "width": 0
              },
              "type": "auto-stats"
            }
          ],
          "id": "f9a2c74c-16ec-4384-9937-c743d30dd791",
          "settings": {
            "gap": 8,
            "padding": 8,
            "title": "Stats"
          },
          "type": "section"
        },
        {
          "children": [
            {
              "children": [
                {
                  "children": [
                    {
                      "children": [],
                      "id": "184fd273-d3a8-4fd3-a496-22ddfeb22603",
                      "settings": {
                        "columns": 6,
                        "formula": "",
                        "gap": 4,
                        "padding": 0
                      },
                      "type": "auto-saving-throws"
                    }
                  ],
                  "id": "434380cd-f499-4a07-848a-94757dccc9e8",
                  "settings": {
                    "description": "Saving throws represent a **character's ability to resist or avoid harmful effects**. Each saving throw is tied to one of the six ability scores (STR, DEX, CON, INT, WIS, CHA).\n\nThey are used to **determine if a character can withstand something happening to them** — spells, traps, poison, fear, or any forced effect.\n\n*The calculation of saving throw modifier is:*\n**(Stat mod)** + **(proficiency bonus if proficient)**",
                    "gap": 8,
                    "grow": false,
                    "padding": 8,
                    "title": "Saving throws",
                    "width": 0
                  },
                  "type": "section"
                },
                {
                  "children": [
                    {
                      "children": [],
                      "id": "36adf72a-6075-496f-a9f5-5245ee10f75c",
                      "settings": {
                        "columns": 2,
                        "gap": 5,
                        "padding": 0
                      },
                      "type": "auto-skills"
                    }
                  ],
                  "id": "32717a86-e36e-429e-8a33-fa537f1be17a",
                  "settings": {
                    "description": "Skills represent **specific areas of expertise a character can train in**. Each skill is tied to one of the six ability scores (STR, DEX, CON, INT, WIS, CHA).\n\nThey are used to check how good a character did something, based on what skill correlates to the action he will perform.\n\n*The calculation of skills modifier its:*\n**(Stat mod)** + **(proficiency bonus if profficient)**",
                    "gap": 8,
                    "grow": true,
                    "padding": 8,
                    "title": "Skills",
                    "width": 0
                  },
                  "type": "section"
                },
                {
                  "children": [
                    {
                      "children": [],
                      "id": "94300411-9ce2-4d2d-b329-bc38f42f75ce",
                      "settings": {
                        "gap": 0,
                        "padding": 0,
                        "width": 0
                      },
                      "type": "features-and-traits"
                    }
                  ],
                  "id": "cbb021f1-b7a2-4bbe-b1de-de0333f5c14e",
                  "settings": {
                    "description": "",
                    "direction": "column",
                    "gap": 8,
                    "padding": 8,
                    "title": "Features & Traits",
                    "width": 0
                  },
                  "type": "section"
                }
              ],
              "id": "84774db3-c5ce-4d65-a9fd-fc22af06da51",
              "settings": {
                "direction": "vertical",
                "gap": 10,
                "padding": 0,
                "title": "Container",
                "width": 0
              },
              "type": "container"
            },
            {
              "children": [
                {
                  "children": [],
                  "id": "13587f34-6c26-4bd2-8f99-833f253eb00c",
                  "settings": {
                    "direction": "horizontal",
                    "gap": 0,
                    "height": 0,
                    "label": "Proficiency Bonus",
                    "padding": 0,
                    "shieldView": true,
                    "showSign": true,
                    "value": "Math.floor(({{level}} - 1) / 4) + 2",
                    "width": 0
                  },
                  "type": "static-counter"
                },
                {
                  "children": [],
                  "id": "b223c976-8f02-4807-9d94-c4e5bea1bc3e",
                  "settings": {
                    "direction": "horizontal",
                    "gap": 0,
                    "height": 0,
                    "label": "Heroic Inspiration",
                    "padding": 0,
                    "shieldView": true,
                    "value": "0",
                    "width": 0
                  },
                  "type": "static-counter"
                },
                {
                  "children": [
                    {
                      "children": [
                        {
                          "children": [],
                          "id": "39d64b76-9569-49ca-9976-2001e23c979b",
                          "settings": {
                            "direction": "vertical",
                            "gap": 0,
                            "height": 92,
                            "label": "HP",
                            "padding": 0,
                            "shieldView": true,
                            "value": "10",
                            "width": 15
                          },
                          "type": "static-counter"
                        },
                        {
                          "children": [],
                          "id": "bce1ccb4-c308-48c8-813d-ee68e82d754a",
                          "settings": {
                            "direction": "vertical",
                            "gap": 0,
                            "height": 92,
                            "label": "AC",
                            "padding": 0,
                            "shieldView": true,
                            "value": "10",
                            "width": 15
                          },
                          "type": "static-counter"
                        },
                        {
                          "children": [
                            {
                              "children": [],
                              "id": "3a3e7c3b-9857-45b3-ac83-206430b37f7b",
                              "settings": {
                                "direction": "horizontal",
                                "gap": 0,
                                "height": 0,
                                "label": "Initiative",
                                "padding": 0,
                                "shieldView": true,
                                "value": "{{stat.dex.mod}}",
                                "width": 0
                              },
                              "type": "static-counter"
                            },
                            {
                              "children": [],
                              "id": "2e166ed7-3518-4508-a51a-80b4fe76a651",
                              "settings": {
                                "direction": "horizontal",
                                "gap": 0,
                                "height": 0,
                                "label": "Speed",
                                "padding": 0,
                                "shieldView": true,
                                "value": "{{specie.movement.walk}} Ft",
                                "width": 0
                              },
                              "type": "static-counter"
                            }
                          ],
                          "id": "23242ea8-c116-4293-a03c-48880e0647cd",
                          "settings": {
                            "direction": "vertical",
                            "gap": 8,
                            "padding": 0,
                            "title": "Container",
                            "width": 0
                          },
                          "type": "container"
                        }
                      ],
                      "id": "10b7696d-9046-4f19-88ae-073e15f1f710",
                      "settings": {
                        "direction": "horizontal",
                        "gap": 8,
                        "padding": 0,
                        "title": "Container",
                        "width": 0
                      },
                      "type": "container"
                    }
                  ],
                  "id": "a85371bd-0c84-46ac-9fff-66f6fa2e6f03",
                  "settings": {
                    "description": "",
                    "direction": "row",
                    "gap": 8,
                    "padding": 8,
                    "title": "Combat",
                    "width": 0
                  },
                  "type": "section"
                },
                {
                  "children": [
                    {
                      "children": [],
                      "id": "432a2853-c858-4f71-80b4-2dda710324f5",
                      "settings": {
                        "gap": 0,
                        "label": "Ideals",
                        "multiline": true,
                        "padding": 0,
                        "placeholder": "",
                        "width": 0
                      },
                      "type": "text-input"
                    },
                    {
                      "children": [],
                      "id": "621c777d-e377-4a11-be34-f11c6c013d81",
                      "settings": {
                        "gap": 0,
                        "label": "Bonds",
                        "multiline": true,
                        "padding": 0,
                        "placeholder": "",
                        "width": 0
                      },
                      "type": "text-input"
                    },
                    {
                      "children": [],
                      "id": "cff46750-3f8c-4b13-ad11-8b5d080f913b",
                      "settings": {
                        "gap": 0,
                        "label": "Personality Traits",
                        "multiline": true,
                        "padding": 0,
                        "placeholder": "",
                        "width": 0
                      },
                      "type": "text-input"
                    },
                    {
                      "children": [],
                      "id": "1b626bca-75e9-4228-b1c2-53c9a992548a",
                      "settings": {
                        "gap": 0,
                        "label": "Flaws",
                        "multiline": true,
                        "padding": 0,
                        "placeholder": "",
                        "width": 0
                      },
                      "type": "text-input"
                    }
                  ],
                  "id": "60675aff-f291-48e9-bb64-08dce241bdc6",
                  "settings": {
                    "description": "",
                    "direction": "column",
                    "gap": 8,
                    "padding": 8,
                    "title": "Character essence",
                    "width": 0
                  },
                  "type": "section"
                }
              ],
              "id": "bb9f075d-2525-4142-89df-e3d40f2986ff",
              "settings": {
                "direction": "vertical",
                "gap": 10,
                "padding": 0,
                "title": "Container",
                "width": 44
              },
              "type": "container"
            }
          ],
          "id": "c254a6b4-c9f9-48ff-952b-b12ac842a999",
          "settings": {
            "direction": "horizontal",
            "gap": 10,
            "padding": 0,
            "title": "Container",
            "width": 0
          },
          "type": "container"
        }
      ],
      "id": "c8eb3a0e-6033-4be9-9f48-9c48b6a03f47",
      "settings": {
        "direction": "vertical",
        "gap": 10,
        "padding": 0,
        "title": "Container",
        "width": 0
      },
      "type": "container"
    }
  ]
}